{
    "id": 1681,
    "date": "2024-04-26T11:15:21",
    "date_gmt": "2024-04-26T08:15:21",
    "guid": {
        "rendered": "https://iron-swords.co.il/?p=1681"
    },
    "modified": "2024-04-26T11:15:27",
    "modified_gmt": "2024-04-26T08:15:27",
    "slug": "pro-hamas-protests-formerly-pro-palestine",
    "status": "publish",
    "type": "post",
    "link": "https://iron-swords.co.il/facts/pro-hamas-protests-formerly-pro-palestine/",
    "title": {
        "rendered": "Pro-Hamas Protests (formerly Pro-Palestine)"
    },
    "content": {
        "rendered": "\n<p>Pro-<a href=\"https://iron-swords.co.il/hamas/\" data-type=\"page\" data-id=\"86\">Hamas</a> protests are demonstrations and rallies that express support for the Palestinian militant group Hamas and its actions against Israel. <br>These protests have erupted across college campuses in the United States following the outbreak of the Israel-Hamas war in <a href=\"https://iron-swords.co.il/hamas-october-7th-videos/\" data-type=\"page\" data-id=\"1092\">October 2023</a>.</p>\n\n\n\n<p>The protests have been organized by various Pro-<a href=\"https://iron-swords.co.il/hamas/\">Hamas</a> groups and activists who are calling for universities to cut ties with Israel, <br>divest from companies supporting the Israeli occupation, and condemn Israel&#8217;s actions in Gaza. <br>Protesters have also demanded that the U.S. government stop providing military aid and weapons to Israel, <br>While burning American flags and chanting &#8220;Death to America&#8221; </p>\n\n\n\n<p>All (100%) protests have featured chants and slogans that express support for <a href=\"https://iron-swords.co.il/hamas/\">Hamas</a>, a designated terrorist organization. <br>For example, at a protest at Columbia University, a student was heard saying, &#8220;<a href=\"https://youtu.be/2Kas9aY47fw\">We are all Hamas</a>.&#8221; </p>\n\n\n\n<p>While the protesters argue that they aim to support <a href=\"https://iron-swords.co.il/hamas/\">Hamas</a>&#8216;s rights and condemn Israeli actions.</p>\n",
        "protected": false
    },
    "excerpt": {
        "rendered": "<p>It&#8217;s not about Palestine it never was about Palestine it&#8217;s all about &#8220;Death to Jews&#8221;</p>\n",
        "protected": false
    },
    "author": 1,
    "featured_media": 1684,
    "comment_status": "closed",
    "ping_status": "closed",
    "sticky": false,
    "template": "",
    "format": "standard",
    "meta": {
        "wds_primary_category": 53,
        "footnotes": ""
    },
    "categories": [
        53
    ],
    "tags": [
        57
    ],
    "class_list": [
        "post-1681",
        "post",
        "type-post",
        "status-publish",
        "format-standard",
        "has-post-thumbnail",
        "hentry",
        "category-facts",
        "tag-stupid-palestine-supporters"
    ],
    "lang": "en",
    "translations": {
        "en": 1681
    },
    "pll_sync_post": [],
    "_links": {
        "self": [
            {
                "href": "https://iron-swords.co.il/wp-json/wp/v2/posts/1681",
                "targetHints": {
                    "allow": [
                        "GET",
                        "POST",
                        "PUT",
                        "PATCH",
                        "DELETE"
                    ]
                }
            }
        ],
        "collection": [
            {
                "href": "https://iron-swords.co.il/wp-json/wp/v2/posts"
            }
        ],
        "about": [
            {
                "href": "https://iron-swords.co.il/wp-json/wp/v2/types/post"
            }
        ],
        "author": [
            {
                "embeddable": true,
                "href": "https://iron-swords.co.il/wp-json/wp/v2/users/1"
            }
        ],
        "replies": [
            {
                "embeddable": true,
                "href": "https://iron-swords.co.il/wp-json/wp/v2/comments?post=1681"
            }
        ],
        "version-history": [
            {
                "count": 3,
                "href": "https://iron-swords.co.il/wp-json/wp/v2/posts/1681/revisions"
            }
        ],
        "predecessor-version": [
            {
                "id": 1685,
                "href": "https://iron-swords.co.il/wp-json/wp/v2/posts/1681/revisions/1685"
            }
        ],
        "wp:featuredmedia": [
            {
                "embeddable": true,
                "href": "https://iron-swords.co.il/wp-json/wp/v2/media/1684"
            }
        ],
        "wp:attachment": [
            {
                "href": "https://iron-swords.co.il/wp-json/wp/v2/media?parent=1681"
            }
        ],
        "wp:term": [
            {
                "taxonomy": "category",
                "embeddable": true,
                "href": "https://iron-swords.co.il/wp-json/wp/v2/categories?post=1681"
            },
            {
                "taxonomy": "post_tag",
                "embeddable": true,
                "href": "https://iron-swords.co.il/wp-json/wp/v2/tags?post=1681"
            }
        ],
        "curies": [
            {
                "name": "wp",
                "href": "https://api.w.org/{rel}",
                "templated": true
            }
        ]
    }
}