{
    "id": 4367,
    "date": "2023-12-27T15:00:03",
    "date_gmt": "2023-12-27T13:00:03",
    "guid": {
        "rendered": "https://iron-swords.co.il/uncategorized/8426/"
    },
    "modified": "2023-12-27T15:00:03",
    "modified_gmt": "2023-12-27T13:00:03",
    "slug": "8426",
    "status": "publish",
    "type": "post",
    "link": "https://iron-swords.co.il/idf-updates/8426/",
    "title": {
        "rendered": "&#8220;Unearthing the Giant: The Story Behind the Discovery of the World&#8217;s Largest Tunnel&#8221;"
    },
    "content": {
        "rendered": "<p>The story behind the discovery of the largest tunnel:<br />\nHow is a tunnel exposed?</p>\n<p>https://www.idf.il/166974</p>\n",
        "protected": false
    },
    "excerpt": {
        "rendered": "<p>The story behind the discovery of the largest tunnel: How is a tunnel exposed? https://www.idf.il/166974</p>\n",
        "protected": false
    },
    "author": 1,
    "featured_media": 0,
    "comment_status": "closed",
    "ping_status": "closed",
    "sticky": false,
    "template": "wp-custom-template-idf-updates",
    "format": "standard",
    "meta": {
        "wds_primary_category": 1,
        "footnotes": ""
    },
    "categories": [
        199
    ],
    "tags": [],
    "class_list": [
        "post-4367",
        "post",
        "type-post",
        "status-publish",
        "format-standard",
        "hentry",
        "category-idf-updates"
    ],
    "lang": "en",
    "translations": {
        "en": 4367
    },
    "pll_sync_post": [],
    "_links": {
        "self": [
            {
                "href": "https://iron-swords.co.il/wp-json/wp/v2/posts/4367",
                "targetHints": {
                    "allow": [
                        "GET",
                        "POST",
                        "PUT",
                        "PATCH",
                        "DELETE"
                    ]
                }
            }
        ],
        "collection": [
            {
                "href": "https://iron-swords.co.il/wp-json/wp/v2/posts"
            }
        ],
        "about": [
            {
                "href": "https://iron-swords.co.il/wp-json/wp/v2/types/post"
            }
        ],
        "author": [
            {
                "embeddable": true,
                "href": "https://iron-swords.co.il/wp-json/wp/v2/users/1"
            }
        ],
        "replies": [
            {
                "embeddable": true,
                "href": "https://iron-swords.co.il/wp-json/wp/v2/comments?post=4367"
            }
        ],
        "version-history": [
            {
                "count": 0,
                "href": "https://iron-swords.co.il/wp-json/wp/v2/posts/4367/revisions"
            }
        ],
        "wp:attachment": [
            {
                "href": "https://iron-swords.co.il/wp-json/wp/v2/media?parent=4367"
            }
        ],
        "wp:term": [
            {
                "taxonomy": "category",
                "embeddable": true,
                "href": "https://iron-swords.co.il/wp-json/wp/v2/categories?post=4367"
            },
            {
                "taxonomy": "post_tag",
                "embeddable": true,
                "href": "https://iron-swords.co.il/wp-json/wp/v2/tags?post=4367"
            }
        ],
        "curies": [
            {
                "name": "wp",
                "href": "https://api.w.org/{rel}",
                "templated": true
            }
        ]
    }
}